odoo8_addon_mgmtsystem_review-8.0.1.0.0.99.dev13-nspkg.pth
odoo_addons/mgmtsystem_review/README.rst
odoo_addons/mgmtsystem_review/__init__.py
odoo_addons/mgmtsystem_review/__openerp__.py
odoo_addons/mgmtsystem_review/data/ir_sequence.xml
odoo_addons/mgmtsystem_review/i18n/de.po
odoo_addons/mgmtsystem_review/i18n/es.po
odoo_addons/mgmtsystem_review/i18n/fr.po
odoo_addons/mgmtsystem_review/i18n/hr.po
odoo_addons/mgmtsystem_review/i18n/id.po
odoo_addons/mgmtsystem_review/i18n/mgmtsystem_review.pot
odoo_addons/mgmtsystem_review/i18n/nb.po
odoo_addons/mgmtsystem_review/i18n/pt_BR.po
odoo_addons/mgmtsystem_review/i18n/sl.po
odoo_addons/mgmtsystem_review/i18n/sv.po
odoo_addons/mgmtsystem_review/i18n/vi.po
odoo_addons/mgmtsystem_review/models/__init__.py
odoo_addons/mgmtsystem_review/models/mgmtsystem_review.py
odoo_addons/mgmtsystem_review/report/__init__.py
odoo_addons/mgmtsystem_review/report/review_report.py
odoo_addons/mgmtsystem_review/report/review_report.rml
odoo_addons/mgmtsystem_review/report/review_report.xml
odoo_addons/mgmtsystem_review/security/ir.model.access.csv
odoo_addons/mgmtsystem_review/security/mgmtsystem_review_security.xml
odoo_addons/mgmtsystem_review/static/description/icon.png
odoo_addons/mgmtsystem_review/views/mgmtsystem_review.xml
odoo8_addon_mgmtsystem_review-8.0.1.0.0.99.dev13.dist-info/METADATA
odoo8_addon_mgmtsystem_review-8.0.1.0.0.99.dev13.dist-info/WHEEL
odoo8_addon_mgmtsystem_review-8.0.1.0.0.99.dev13.dist-info/namespace_packages.txt
odoo8_addon_mgmtsystem_review-8.0.1.0.0.99.dev13.dist-info/top_level.txt
odoo8_addon_mgmtsystem_review-8.0.1.0.0.99.dev13.dist-info/RECORD
